{
    "ad4m.at": ["ad4m\\.at"],
    "addthis.com": ["addthis\\.com\\/static","addthis\\.com\\/e","addthis\\.com\\/js", "addthis\\.com\\/live\\/red_lojson"],
    "adingo.jp": ["adingo\\.jp"],
    "admanmedia.com": ["admanmedia\\.com"],
    "adnami.io": ["adnami\\.io\\/macro\\/spec\\/adsm\\.macro"],
    "aticdn.net": ["aticdn\\.net"],
    "avis-verifies.com": ["avis-verifies\\.com\\/fr\\/widget4", "avis-verifies\\.com\\/fr\\/cache"],
    "bing.com": ["bing\\.com\\/p\\/action", "bing\\.com\\/rp","bing\\.com\\/vs\\/ec"],
    "brand-display.com": ["brand-display\\.com"],
    "bttrack.com": ["bttrack\\.com"],
    "civiccomputing.com": ["civiccomputing\\.com\\/8", "civiccomputing\\.com\\/9"],
    "consensu.org": ["consensu\\.org"],
    "cookiebot.com": ["cookiebot\\.com"],
    "cookielaw.org": ["cookielaw\\.org"],
    "de17a.com": ["de17a\\.com"],
    "dmcdn.net": ["dmcdn\\.net\\/playerv5"],
    "edgekey.net": ["edgekey\\.net"],
    "ezodn.com": ["ezodn\\.com"],
    "facebook.com": ["facebook\\.com\\/rsrc\\.php"],
    "facebook.net": ["facebook\\.net\\/signals\\/config"],
    "fiftyt.com": ["fiftyt\\.com"],
    "hs-banner.com": ["hs-banner\\.com"],
    "hubspot.com": ["hubspot\\.com\\/cta\\/default", "hubspot\\.com\\/analytics"],
    "impact-ad.jp": ["impact-ad\\.jp"],
    "klaviyo.com": ["klaviyo\\.com"],
    "marketo.net": ["marketo\\.net"],
    "omappapi.com": ["omappapi\\.com"],
    "onetag-sys.com": ["onetag-sys\\.com"],
    "onetrust.com": ["onetrust\\.com\\/scripttemplates", "onetrust\\.com\\/dsarwebform\\/6"],
    "qualtrics.com": ["qualtrics\\.com\\/jfe", "qualtrics\\.com\\/dxjsmodule"],
    "reddit.com": ["reddit\\.com\\/static", "reddit\\.com\\/r"],
    "resetdigital.co": ["resetdigital\\.co"],
    "richaudience.com": ["richaudience\\.com"],
    "servenobid.com": ["servenobid\\.com"],
    "serverbid.com": ["serverbid\\.com"],
    "sharethis.com": ["sharethis\\.com"],
    "smadex.com": ["smadex\\.com"],
    "snapchat.com": ["snapchat\\.com\\/cm"],
    "sp-prod.net": ["sp-prod\\.net"],
    "sportradarserving.com": ["sportradarserving\\.com\\/ul_cb"],
    "tiktok.com": ["tiktok\\.com\\/i18n\\/pixel"],
    "trustarc.com": ["trustarc\\.com\\/asset", "trustarc\\.com\\/v2\\/notice", "trustarc\\.com\\/defaultpreferencemanager"],
    "trustpilot.com": ["trustpilot\\.com\\/trustboxes", "trustpilot\\.com\\/v2\\.1\\/js"],
    "twitter.com": ["twitter\\.com\\/widgets", "twitter\\.com\\/embed", "twitter\\.com\\/js", "twitter\\.com\\/1"],
    "tynt.com": ["tynt\\.com"],
    "unrulymedia.com": ["unrulymedia\\.com"],
    "videoplayerhub.com": ["videoplayerhub\\.com"],
    "yahoo.com": ["yahoo\\.com\\/sync", "yahoo\\.com\\/ups", "yahoo\\.com\\/a"],
    "yandex.com": ["yandex\\.com\\/watch", "yandex\\.com\\/sync_cookie"],
    "zeotap.com": ["zeotap\\.com"],
    "zip.co": [],
    "zipmoney.com.au": []
}